xpsieve/__init__.py
xpsieve/xpsieve.py
xpsieve-0.4.0.dist-info/WHEEL
xpsieve-0.4.0.dist-info/METADATA
xpsieve-0.4.0.dist-info/RECORD
